{
  "library": "spring-mvc",
  "dateLibrary": "Legacy",
  "useTags": true,
  "hideGenerationTimestamp": true,
  "modelPackage": "oracle.fsgbu.cashflowRecon.api.model",
  "apiPackage": "oracle.fsgbu.cashflowRecon.web.api",
  "invokerPackage": "oracle.fsgbu.cashflowRecon",
  "importMappings": {
		"ResponseDtoWrapper": "oracle.fsgbu.gus.response.dto.ResponseDtoWrapper",
		"GenericDto" : "oracle.fsgbu.gus.common.dto.GenericDto",
		"ReconTxnDto" : "oracle.fsgbu.manualRecon.api.model.ReconTxnDto",
		"ExpDrCrPayReconDtoCollection" : "oracle.fsgbu.manualRecon.api.model.ExpDrCrPayReconDtoCollection" ,
		"ExpDrCrPaymentCollection" : "oracle.fsgbu.manualRecon.api.model.ExpDrCrPaymentCollection",
		"ExpDrCrPmtSearchModel" : "oracle.fsgbu.manualRecon.api.model.ExpDrCrPmtSearchModel",
		"CashflowResponse" : "oracle.fsgbu.manualRecon.api.model.CashflowResponse"
	}
}